crem/__init__.py
crem/arg_types.py
crem/crem.py
crem/frag_to_env_mp.py
crem/fragmentation.py
crem/functions.py
crem/guacamol_crem_test.py
crem/guacamol_distribution_test.py
crem/import_env_to_db.py
crem/mol_context.py
crem/utils.py
crem/scripts/__init__.py
crem/scripts/crem_add_prop.py
crem/scripts/crem_create_frag_db.sh
crem/scripts/enumerate_molecules.py
crem/scripts/get_stat.py
crem/scripts/r1.txt
crem/scripts/select_ids.py
crem-0.2.16.data/scripts/crem_create_frag_db.sh
crem-0.2.16.dist-info/LICENSE.txt
crem-0.2.16.dist-info/METADATA
crem-0.2.16.dist-info/WHEEL
crem-0.2.16.dist-info/entry_points.txt
crem-0.2.16.dist-info/top_level.txt
crem-0.2.16.dist-info/RECORD
